easygit/__init__.py
easygit/easygit.py
easygit-1.0.4.dist-info/LICENSE
easygit-1.0.4.dist-info/METADATA
easygit-1.0.4.dist-info/WHEEL
easygit-1.0.4.dist-info/top_level.txt
easygit-1.0.4.dist-info/RECORD
