Metadata-Version: 2.1
Name: easygit
Version: 1.0.4
Summary: Library to learn git
Home-page: UNKNOWN
Author: Sharan Babu
Author-email: sharanbabu2001@gmail.com
License: UNKNOWN
Keywords: python,chatbot,git,interactive terminal
Platform: UNKNOWN
Classifier: Development Status :: 5 - Production/Stable
Classifier: Intended Audience :: Developers
Classifier: Topic :: Software Development :: Build Tools
Classifier: License :: OSI Approved :: MIT License
Classifier: Programming Language :: Python :: 3
License-File: LICENSE
Requires-Dist: wit
Requires-Dist: colorama
